ChangeLog
LICENSE
MANIFEST.in
README.md
setup.cfg
setup.py
django_hisstory.egg-info/PKG-INFO
django_hisstory.egg-info/SOURCES.txt
django_hisstory.egg-info/dependency_links.txt
django_hisstory.egg-info/requires.txt
django_hisstory.egg-info/top_level.txt
hisstory/__init__.py
hisstory/models.py
hisstory/locale/ru/LC_MESSAGES/django.mo
hisstory/locale/ru/LC_MESSAGES/django.po