Metadata-Version: 1.1
Name: django-hisstory
Version: 0.1.2
Summary: Lightweight read-only django model history app.
Home-page: https://bitbucket.org/medsafe/django-hisstory
Author: Andrey Mozgunov
Author-email: andrey.mozgunov@softline.ru
License: New BSD License
Keywords: django apps
Platform: UNKNOWN
Classifier: Development Status :: 2 - Pre-Alpha
Classifier: Environment :: Plugins
Classifier: Framework :: Django
Classifier: Intended Audience :: Developers
Classifier: License :: OSI Approved :: BSD License
Classifier: Programming Language :: Python
Classifier: Topic :: Software Development :: Libraries :: Python Modules
